<?xml version="1.0" encoding="UTF-8"?>
<?xml-stylesheet type="text/css" href="BookInfo.css"?>
<Movie>
<M>
<Mno>1</Mno>
<Mname>Agni Path</Mname>
<Actorname>Hritik Roshan</Actorname>
<Ryear>2016</Ryear>
</M><M>
<Mno>2</Mno>
<Mname>Avenger endgame</Mname>
<Actorname>RDJ</Actorname>
<Ryear>2020</Ryear>
</M>
<M>
<Mno>3</Mno>
<Mname>AVATAR -2</Mname>
<Actorname>RR Martin</Actorname>
<Ryear>2016</Ryear>
</M>
<M>
<Mno>4</Mno>
<Mname>AVATAR -3</Mname>
<Actorname>AAMartin</Actorname>
<Ryear>2017</Ryear>
</M>
</Movie>
